{"name":"Shuangyan001.com","tagline":"","body":"$ git clone git@github.com:yijin/shuangyan001.com.git //本地如果无远程代码，先做这步，不然就忽略\r\n\r\n$ cd .ssh/yijin.github.com //定位到你blog的目录下\r\n\r\n$ git pull origin master //先同步远程文件，后面的参数会自动连接你远程的文件\r\n\r\n$ git status //查看本地自己修改了多少文件\r\n\r\n$ git add . //添加远程不存在的git文件\r\n\r\n$ git commit * -m \"what I want told to someone\"\r\n\r\n$ git push origin master //更新到远程服务器上","google":"","note":"Don't delete this file! It's used internally to help with page regeneration."}